BNumMet/Interpolation.py
BNumMet/LinearSystems.py
BNumMet/NonLinear.py
BNumMet/Random.py
BNumMet/__init__.py
BNumMet/module.py
BNumMet/Visualizers/InterpolationVisualizer.py
BNumMet/Visualizers/LUVisualizer.py
BNumMet/Visualizers/LeastSquaresVisualizer.py
BNumMet/Visualizers/NonLinearVisualizer.py
BNumMet/Visualizers/RandomVisualizer.py
BNumMet-1.0.0.dist-info/LICENSE
BNumMet-1.0.0.dist-info/METADATA
BNumMet-1.0.0.dist-info/WHEEL
BNumMet-1.0.0.dist-info/top_level.txt
BNumMet-1.0.0.dist-info/RECORD
